bibleparser/__init__.py
bibleparser/bibleparser.py
bibleparser/book_chapter_verses.py
bibleparser-0.0.2.dist-info/LICENSE
bibleparser-0.0.2.dist-info/METADATA
bibleparser-0.0.2.dist-info/WHEEL
bibleparser-0.0.2.dist-info/top_level.txt
bibleparser-0.0.2.dist-info/RECORD
