Metadata-Version: 2.1
Name: bibleparser
Version: 0.0.2
Summary: Parse a mistranscribed dictated bible reference into a standard format
Author-email: Taylor Vance <mirrors.cities0w@icloud.com>
License: MIT
Project-URL: Homepage, https://github.com/taylorvance/bibleparser
Project-URL: Issues, https://github.com/taylorvance/bibleparser/issues
Keywords: bible,parser,reference,passage,dictation,transcription,text processing,siri,alexa
Classifier: Programming Language :: Python :: 3
Classifier: License :: OSI Approved :: MIT License
Classifier: Operating System :: OS Independent
Requires-Python: >=3.8
License-File: LICENSE
